pincushion/__init__.py
pincushion/archive.py
pincushion/historypin.py
pincushion/templates/base.html
pincushion/templates/collection.html
pincushion/templates/index.html
pincushion/templates/map.html
pincushion/templates/pin.html
pincushion/templates/tag.html
pincushion/templates/tags.html
pincushion/templates/leaflet/leaflet.css
pincushion/templates/leaflet/leaflet.js
pincushion/templates/leaflet/images/layers-2x.png
pincushion/templates/leaflet/images/layers.png
pincushion/templates/leaflet/images/marker-icon-2x.png
pincushion/templates/leaflet/images/marker-icon.png
pincushion/templates/leaflet/images/marker-shadow.png
pincushion/templates/leaflet/leaflet.markercluster/MarkerCluster.Default.css
pincushion/templates/leaflet/leaflet.markercluster/MarkerCluster.css
pincushion/templates/leaflet/leaflet.markercluster/leaflet.markercluster.js
pincushion-0.5.0.dist-info/METADATA
pincushion-0.5.0.dist-info/WHEEL
pincushion-0.5.0.dist-info/entry_points.txt
pincushion-0.5.0.dist-info/RECORD
