Metadata-Version: 2.4
Name: pincushion
Version: 0.5.0
Summary: An archiving tool for Historypin
Requires-Python: >=3.9
Requires-Dist: click>=8.1.7
Requires-Dist: jinja2>=3.1.4
Requires-Dist: requests>=2.32.3
Requires-Dist: tqdm>=4.66.5
Requires-Dist: yt-dlp>=2024.9.27
